fastidius/__init__.py
fastidius/cli.py
fastidius/app_template/.gitignore
fastidius/app_template/README.md
fastidius/app_template/docker-compose.yml
fastidius/app_template/.github/workflows/test_and_deploy.yml
fastidius/app_template/.vscode/launch.json
fastidius/app_template/backend/Dockerfile
fastidius/app_template/backend/__init__.py
fastidius/app_template/backend/db-sqlalchemy.py
fastidius/app_template/backend/db.py
fastidius/app_template/backend/main-sqlalchemy.py
fastidius/app_template/backend/main.py
fastidius/app_template/backend/requirements.txt
fastidius/app_template/backend/api/__init__.py
fastidius/app_template/backend/api/endpoints/user_endpoints.py
fastidius/app_template/backend/core/__init__.py
fastidius/app_template/backend/core/auth-sqlalchemy.py
fastidius/app_template/backend/core/auth.py
fastidius/app_template/backend/core/settings/base.py
fastidius/app_template/backend/core/settings/config.py
fastidius/app_template/backend/core/settings/dev.py
fastidius/app_template/backend/core/settings/prod.py
fastidius/app_template/backend/core/settings/test.py
fastidius/app_template/backend/crud/__init__.py
fastidius/app_template/backend/models/__init__.py
fastidius/app_template/backend/models/user.py
fastidius/app_template/frontend/.editorconfig
fastidius/app_template/frontend/.postcssrc.js
fastidius/app_template/frontend/Dockerfile
fastidius/app_template/frontend/babel.config.js
fastidius/app_template/frontend/jsconfig.json
fastidius/app_template/frontend/package.json
fastidius/app_template/frontend/quasar.conf.js
fastidius/app_template/frontend/.quasar/app.js
fastidius/app_template/frontend/.quasar/client-entry.js
fastidius/app_template/frontend/.quasar/client-prefetch.js
fastidius/app_template/frontend/.quasar/quasar-user-options.js
fastidius/app_template/frontend/.vscode/extensions.json
fastidius/app_template/frontend/.vscode/settings.json
fastidius/app_template/frontend/public/favicon.ico
fastidius/app_template/frontend/public/icons/favicon-128x128.png
fastidius-0.0.15.dist-info/LICENSE
fastidius-0.0.15.dist-info/METADATA
fastidius-0.0.15.dist-info/WHEEL
fastidius-0.0.15.dist-info/entry_points.txt
fastidius-0.0.15.dist-info/top_level.txt
fastidius-0.0.15.dist-info/RECORD
