Metadata-Version: 2.1
Name: fastidius
Version: 0.0.15
Summary: A full stack web app creator with FastAPI
Home-page: https://github.com/johnckealy/fastidius
Author: John Kealy
Author-email: johnckealy.dev@gmail.com
License: MIT
Platform: UNKNOWN
Classifier: Programming Language :: Python :: 3.9
Classifier: Operating System :: OS Independent
Requires-Python: >=3.9
License-File: LICENSE
Requires-Dist: click (==8.0.4)
Requires-Dist: fabric
Requires-Dist: mako
Requires-Dist: setuptools
Requires-Dist: twine
Requires-Dist: typer
Requires-Dist: uvicorn
